easier_install.py
setup.py
easier_install.egg-info/PKG-INFO
easier_install.egg-info/SOURCES.txt
easier_install.egg-info/dependency_links.txt
easier_install.egg-info/entry_points.txt
easier_install.egg-info/top_level.txt
