Metadata-Version: 1.0
Name: easier-install
Version: 0.1
Summary: Create setup.py files for a number of modules and scripts quickly
Home-page: http://opensvn.csie.org/vvprj/trunk/easier_install/
Author: Ville M. Vainio
Author-email: vivainio@gmail.com
License: MIT Open Source License
Platform: UNKNOWN
